fastshap/KernelExplainer.py
fastshap/__init__.py
fastshap/compat.py
fastshap/plotting.py
fastshap/utils.py
fastshap-0.3.1.dist-info/METADATA
fastshap-0.3.1.dist-info/WHEEL
fastshap-0.3.1.dist-info/top_level.txt
fastshap-0.3.1.dist-info/RECORD
