Metadata-Version: 2.1
Name: fastshap
Version: 0.3.1
Summary: Fast SHAP kernel explainer
Home-page: https://github.com/AnotherSamWilson/fastshap
Author: Samuel Wilson
Author-email: samwilson303@gmail.com
License: MIT
Keywords: shap,model explainability
Platform: UNKNOWN
Classifier: Natural Language :: English
Classifier: Operating System :: MacOS
Classifier: Operating System :: Microsoft :: Windows
Classifier: Programming Language :: Python :: 3.7
Classifier: Programming Language :: Python :: 3.8
Classifier: Programming Language :: Python :: 3.9
Classifier: License :: OSI Approved :: MIT License
Classifier: Operating System :: OS Independent
Requires-Python: >=3.7
Requires-Dist: numpy
Requires-Dist: pandas
Requires-Dist: sklearn
